mongorm/__init__.py
mongorm/exceptions.py
mongorm/index.py
mongorm/mongorm.py
mongorm/version.py
python_mongorm-0.1.1.dist-info/LICENSE.md
python_mongorm-0.1.1.dist-info/METADATA
python_mongorm-0.1.1.dist-info/WHEEL
python_mongorm-0.1.1.dist-info/RECORD
