Metadata-Version: 2.1
Name: python-mongorm
Version: 0.1.1
Summary: MongORM is an ORM (object relational mapping) wrapper using async library motor for MongoDB connection and pydantic for data definition and validation.
Home-page: https://github.com/tomasvotava/mongorm
License: MIT
Keywords: mongodb,mongo,orm
Author: Tomas Votava
Author-email: info@tomasvotava.eu
Requires-Python: >=3.10,<4.0
Classifier: License :: OSI Approved :: MIT License
Classifier: Programming Language :: Python :: 3
Classifier: Programming Language :: Python :: 3.10
Classifier: Programming Language :: Python :: 3.11
Requires-Dist: motor (>=3.1.1,<4.0.0)
Requires-Dist: pydantic (>=1.10.5,<2.0.0)
Project-URL: Documentation, https://tomasvotava.github.io/mongorm/
Project-URL: Repository, https://github.com/tomasvotava/mongorm
